openbb_mcp_server/__init__.py
openbb_mcp_server/app/__init__.py
openbb_mcp_server/app/app.py
openbb_mcp_server/app/auth.py
openbb_mcp_server/models/__init__.py
openbb_mcp_server/models/mcp_config.py
openbb_mcp_server/models/prompts.py
openbb_mcp_server/models/registry.py
openbb_mcp_server/models/settings.py
openbb_mcp_server/models/tools.py
openbb_mcp_server/py.typed
openbb_mcp_server/service/__init__.py
openbb_mcp_server/service/mcp_service.py
openbb_mcp_server/utils/__init__.py
openbb_mcp_server/utils/app_import.py
openbb_mcp_server/utils/fastapi.py
openbb_mcp_server-1.2.2.dist-info/METADATA
openbb_mcp_server-1.2.2.dist-info/WHEEL
openbb_mcp_server-1.2.2.dist-info/entry_points.txt
openbb_mcp_server-1.2.2.dist-info/RECORD
