Metadata-Version: 2.4
Name: openbb-mcp-server
Version: 1.2.2
Summary: OpenBB Platform MCP Server
License: AGPL-3.0-only
Author: OpenBB
Author-email: hello@openbb.co
Requires-Python: >=3.10,<3.14
Classifier: License :: OSI Approved :: GNU Affero General Public License v3
Classifier: Programming Language :: Python :: 3
Classifier: Programming Language :: Python :: 3.10
Classifier: Programming Language :: Python :: 3.11
Classifier: Programming Language :: Python :: 3.12
Classifier: Programming Language :: Python :: 3.13
Requires-Dist: fastmcp (>=2.14.1)
Requires-Dist: mcp (>=1.23.0)
Requires-Dist: openbb-core (>=1.5.7,<2.0.0)
Project-URL: Documentation, https://docs.openbb.co
Project-URL: Homepage, https://openbb.co
Project-URL: Repository, https://github.com/openbb-finance/openbb
